guac/__init__.py
guac/functions.py
guac/instances.py
guac/monad.py
guac-1.0.0.dist-info/.DS_Store
guac-1.0.0.dist-info/DESCRIPTION.rst
guac-1.0.0.dist-info/METADATA
guac-1.0.0.dist-info/RECORD
guac-1.0.0.dist-info/WHEEL
guac-1.0.0.dist-info/metadata.json
guac-1.0.0.dist-info/top_level.txt
guac-1.0.0.dist-info/zip-safe
