Metadata-Version: 2.0
Name: guac
Version: 1.0.0
Summary: Monadic do-notation in Python
Home-page: https://github.com/JadenGeller/Guac
Author: Jaden Geller
Author-email: UNKNOWN
License: MIT
Download-URL: https://github.com/JadenGeller/Guac/archive/1.0.0.tar.gz
Keywords: monad,monadic,coroutine,generator,pypy,backtracking
Platform: UNKNOWN
Classifier: Intended Audience :: Developers
Classifier: Intended Audience :: Education
Classifier: Topic :: Software Development :: Libraries
Classifier: License :: OSI Approved :: MIT License
Classifier: Programming Language :: Python :: 3 :: Only
Classifier: Programming Language :: Python :: Implementation :: PyPy
